scalr/__init__.py
scalr/app.py
scalr/config.py
scalr/log.py
scalr/metric.py
scalr/scalr.py
scalr/version.py
scalr/cloud/__init__.py
scalr/cloud/factory.py
scalr/cloud/adapters/__init__.py
scalr/cloud/adapters/cloudscale_ch.py
scalr/cloud/adapters/cloudstack.py
scalr/cloud/adapters/digitalocean.py
scalr/cloud/adapters/dummy.py
scalr/cloud/adapters/hcloud.py
scalr/cloud/adapters/vultr.py
scalr/policy/__init__.py
scalr/policy/factory.py
scalr/policy/adapters/__init__.py
scalr/policy/adapters/dummy.py
scalr/policy/adapters/prometheus.py
scalr/policy/adapters/time.py
scalr/policy/adapters/web.py
scalr_ngine-0.23.1.dist-info/licenses/LICENSE
scalr_ngine-0.23.1.dist-info/METADATA
scalr_ngine-0.23.1.dist-info/WHEEL
scalr_ngine-0.23.1.dist-info/entry_points.txt
scalr_ngine-0.23.1.dist-info/top_level.txt
scalr_ngine-0.23.1.dist-info/RECORD
