Metadata-Version: 2.4
Name: scalr-ngine
Version: 0.23.1
Summary: Autoscaling for Clouds.
Home-page: https://github.com/ngine-io/scalr
Author: René Moser
Author-email: mail@renemoser.net
License: MIT
Classifier: Intended Audience :: Developers
Classifier: Intended Audience :: System Administrators
Classifier: Development Status :: 4 - Beta
Classifier: Programming Language :: Python :: 3
Classifier: License :: OSI Approved :: MIT License
Classifier: Operating System :: OS Independent
Classifier: Environment :: Web Environment
Requires-Python: >=3.12
License-File: LICENSE
Requires-Dist: certifi==2025.6.15
Requires-Dist: charset-normalizer==3.4.2
Requires-Dist: cloudscale-sdk==0.7.0
Requires-Dist: contourpy==1.3.2
Requires-Dist: cs==3.3.1
Requires-Dist: cycler==0.12.1
Requires-Dist: dateparser==1.2.2
Requires-Dist: deprecated==1.2.18
Requires-Dist: fonttools==4.58.4
Requires-Dist: hcloud==2.5.3
Requires-Dist: httmock==1.4.0
Requires-Dist: idna==3.10
Requires-Dist: importlib-metadata==8.7.0
Requires-Dist: jsonpickle==4.1.1
Requires-Dist: kiwisolver==1.4.8
Requires-Dist: matplotlib==3.10.3
Requires-Dist: numpy==2.3.1
Requires-Dist: packaging==25.0
Requires-Dist: pandas==2.3.0
Requires-Dist: pillow==11.3.0
Requires-Dist: prometheus-api-client==0.6.0
Requires-Dist: prometheus-client==0.22.1
Requires-Dist: pydantic==1.10.22
Requires-Dist: pydantic-yaml==0.11.2
Requires-Dist: pyparsing==3.2.3
Requires-Dist: python-dateutil==2.9.0.post0
Requires-Dist: python-digitalocean==1.17.0
Requires-Dist: python-dotenv==1.1.1
Requires-Dist: python-json-logger==3.3.0
Requires-Dist: pytz==2025.2
Requires-Dist: pyyaml==6.0.2
Requires-Dist: regex==2024.11.6
Requires-Dist: requests==2.32.4
Requires-Dist: schedule==1.2.2
Requires-Dist: six==1.17.0
Requires-Dist: types-deprecated==1.2.15.20250304
Requires-Dist: typing-extensions==4.14.0
Requires-Dist: tzdata==2025.2
Requires-Dist: tzlocal==5.3.1
Requires-Dist: urllib3==2.5.0
Requires-Dist: wrapt==1.17.2
Requires-Dist: xdg==6.0.0
Requires-Dist: zipp==3.23.0
Dynamic: author
Dynamic: author-email
Dynamic: classifier
Dynamic: description
Dynamic: description-content-type
Dynamic: home-page
Dynamic: license
Dynamic: license-file
Dynamic: requires-dist
Dynamic: requires-python
Dynamic: summary
